<?xml version="1.0" encoding="utf-8" ?>
<Defs>

  <WorkTypeDef>
    <defName>Stocking</defName>
    <labelShort>Stock</labelShort>
    <pawnLabel>Stocker</pawnLabel>
    <gerundLabel>stocking</gerundLabel>
    <description>Manage vital stockpiles.</description>
    <verb>Stock</verb>
    <naturalPriority>350</naturalPriority>
    <alwaysStartActive>false</alwaysStartActive>
    <requireCapableColonist>true</requireCapableColonist>
    <workTags>
      <li>Hauling</li>
    </workTags>
  </WorkTypeDef>

</Defs>